{
  "blightsources": {
    "blightstones": {
      "blightfoils": [
        {
          "category": "Blightstones",
          "subcategory": "Blightfoils",
          "name": "Forslone",
          "rarity": 27,
          "description": [
            "Lorem, ipsum dolor sit amet consectetur adipisicing elit. Animi iure omnis perspiciatis veritatis molestiae sit accusamus tenetur, porro quibusdam eum!"
          ],
          "introduced": 1
        },
        {
          "category": "Blightstones",
          "subcategory": "Blightfoils",
          "name": "Erecombe",
          "rarity": 9,
          "description": [
            "Lorem, ipsum dolor sit amet consectetur adipisicing elit. Animi iure omnis perspiciatis veritatis molestiae sit accusamus tenetur, porro quibusdam eum!"
          ],
          "introduced": 1
        },
        {
          "category": "Blightstones",
          "subcategory": "Blightfoils",
          "name": "Voidshimmer",
          "rarity": 1,
          "description": [
            "Lorem, ipsum dolor sit amet consectetur adipisicing elit. Animi iure omnis perspiciatis veritatis molestiae sit accusamus tenetur, porro quibusdam eum!"
          ],
          "introduced": 1
        }
      ],
      "crystali": [
        {
          "category": "Blightstones",
          "subcategory": "Crystali",
          "name": "Apertrite",
          "rarity": 27,
          "description": [
            "Lorem, ipsum dolor sit amet consectetur adipisicing elit. Animi iure omnis perspiciatis veritatis molestiae sit accusamus tenetur, porro quibusdam eum!"
          ],
          "introduced": 1
        },
        {
          "category": "Blightstones",
          "subcategory": "Crystali",
          "name": "Meartite",
          "rarity": 9,
          "description": [
            "Lorem, ipsum dolor sit amet consectetur adipisicing elit. Animi iure omnis perspiciatis veritatis molestiae sit accusamus tenetur, porro quibusdam eum!"
          ],
          "introduced": 1
        },
        {
          "category": "Blightstones",
          "subcategory": "Crystali",
          "name": "Digitrite",
          "rarity": 1,
          "description": [
            "Lorem, ipsum dolor sit amet consectetur adipisicing elit. Animi iure omnis perspiciatis veritatis molestiae sit accusamus tenetur, porro quibusdam eum!"
          ],
          "introduced": 1
        }
      ],
      "lylodes": [
        {
          "category": "Blightstones",
          "subcategory": "Lylodes",
          "name": "Charke",
          "rarity": 27,
          "description": [
            "Lorem, ipsum dolor sit amet consectetur adipisicing elit. Animi iure omnis perspiciatis veritatis molestiae sit accusamus tenetur, porro quibusdam eum!"
          ],
          "introduced": 1
        },
        {
          "category": "Blightstones",
          "subcategory": "Lylodes",
          "name": "Amplare",
          "rarity": 9,
          "description": [
            "Lorem, ipsum dolor sit amet consectetur adipisicing elit. Animi iure omnis perspiciatis veritatis molestiae sit accusamus tenetur, porro quibusdam eum!"
          ],
          "introduced": 1
        },
        {
          "category": "Blightstones",
          "subcategory": "Lylodes",
          "name": "Curos",
          "rarity": 1,
          "description": [
            "Lorem, ipsum dolor sit amet consectetur adipisicing elit. Animi iure omnis perspiciatis veritatis molestiae sit accusamus tenetur, porro quibusdam eum!"
          ],
          "introduced": 1
        }
      ]
    },
    "blightichors": {
      "lifeblight": [
        {
          "category": "Blightichors",
          "subcategory": "Lifeblight",
          "name": "Rigorvat",
          "rarity": 27,
          "description": [
            "Lorem, ipsum dolor sit amet consectetur adipisicing elit. Animi iure omnis perspiciatis veritatis molestiae sit accusamus tenetur, porro quibusdam eum!"
          ],
          "introduced": 1
        },
        {
          "category": "Blightichors",
          "subcategory": "Lifeblight",
          "name": "Purivat",
          "rarity": 9,
          "description": [
            "Lorem, ipsum dolor sit amet consectetur adipisicing elit. Animi iure omnis perspiciatis veritatis molestiae sit accusamus tenetur, porro quibusdam eum!"
          ],
          "introduced": 1
        },
        {
          "category": "Blightichors",
          "subcategory": "Lifeblight",
          "name": "Mirivat",
          "rarity": 1,
          "description": [
            "Lorem, ipsum dolor sit amet consectetur adipisicing elit. Animi iure omnis perspiciatis veritatis molestiae sit accusamus tenetur, porro quibusdam eum!"
          ],
          "introduced": 1
        }
      ],
      "blightvenoms": [
        {
          "category": "Blightichors",
          "subcategory": "Blightvenoms",
          "name": "Perceptyde",
          "rarity": 27,
          "description": [
            "Lorem, ipsum dolor sit amet consectetur adipisicing elit. Animi iure omnis perspiciatis veritatis molestiae sit accusamus tenetur, porro quibusdam eum!"
          ],
          "introduced": 1
        },
        {
          "category": "Blightichors",
          "subcategory": "Blightvenoms",
          "name": "Residux",
          "rarity": 9,
          "description": [
            "Lorem, ipsum dolor sit amet consectetur adipisicing elit. Animi iure omnis perspiciatis veritatis molestiae sit accusamus tenetur, porro quibusdam eum!"
          ],
          "introduced": 1
        },
        {
          "category": "Blightichors",
          "subcategory": "Blightvenoms",
          "name": "Falefate",
          "rarity": 1,
          "description": [
            "Lorem, ipsum dolor sit amet consectetur adipisicing elit. Animi iure omnis perspiciatis veritatis molestiae sit accusamus tenetur, porro quibusdam eum!"
          ],
          "introduced": 1
        }
      ],
      "blightmares": [
        {
          "category": "Blightichors",
          "subcategory": "Blightmares",
          "name": "Blissburn",
          "rarity": 27,
          "description": [
            "Lorem, ipsum dolor sit amet consectetur adipisicing elit. Animi iure omnis perspiciatis veritatis molestiae sit accusamus tenetur, porro quibusdam eum!"
          ],
          "introduced": 1
        },
        {
          "category": "Blightichors",
          "subcategory": "Blightmares",
          "name": "Red Agony",
          "rarity": 9,
          "description": [
            "Lorem, ipsum dolor sit amet consectetur adipisicing elit. Animi iure omnis perspiciatis veritatis molestiae sit accusamus tenetur, porro quibusdam eum!"
          ],
          "introduced": 1
        },
        {
          "category": "Blightichors",
          "subcategory": "Blightmares",
          "name": "Pulsepox",
          "rarity": 1,
          "description": [
            "Lorem, ipsum dolor sit amet consectetur adipisicing elit. Animi iure omnis perspiciatis veritatis molestiae sit accusamus tenetur, porro quibusdam eum!"
          ],
          "introduced": 1
        }
      ]
    },
    "blightfumes": {
      "rushblight": [
        {
          "category": "Blightfumes",
          "subcategory": "Rushblight",
          "name": "Mystic",
          "rarity": 27,
          "description": [
            "Lorem, ipsum dolor sit amet consectetur adipisicing elit. Animi iure omnis perspiciatis veritatis molestiae sit accusamus tenetur, porro quibusdam eum!"
          ],
          "introduced": 1
        },
        {
          "category": "Blightfumes",
          "subcategory": "Rushblight",
          "name": "Surge",
          "rarity": 9,
          "description": [
            "Lorem, ipsum dolor sit amet consectetur adipisicing elit. Animi iure omnis perspiciatis veritatis molestiae sit accusamus tenetur, porro quibusdam eum!"
          ],
          "introduced": 1
        },
        {
          "category": "Blightfumes",
          "subcategory": "Rushblight",
          "name": "Edge",
          "rarity": 1,
          "description": [
            "Lorem, ipsum dolor sit amet consectetur adipisicing elit. Animi iure omnis perspiciatis veritatis molestiae sit accusamus tenetur, porro quibusdam eum!"
          ],
          "introduced": 1
        }
      ],
      "miasmeta": [
        {
          "category": "Blightfumes",
          "subcategory": "Miasmeta",
          "name": "Lasperr",
          "rarity": 27,
          "description": [
            "Lorem, ipsum dolor sit amet consectetur adipisicing elit. Animi iure omnis perspiciatis veritatis molestiae sit accusamus tenetur, porro quibusdam eum!"
          ],
          "introduced": 1
        },
        {
          "category": "Blightfumes",
          "subcategory": "Miasmeta",
          "name": "Manaphage",
          "rarity": 9,
          "description": [
            "Lorem, ipsum dolor sit amet consectetur adipisicing elit. Animi iure omnis perspiciatis veritatis molestiae sit accusamus tenetur, porro quibusdam eum!"
          ],
          "introduced": 1
        },
        {
          "category": "Blightfumes",
          "subcategory": "Miasmeta",
          "name": "Ominox",
          "rarity": 1,
          "description": [
            "Lorem, ipsum dolor sit amet consectetur adipisicing elit. Animi iure omnis perspiciatis veritatis molestiae sit accusamus tenetur, porro quibusdam eum!"
          ],
          "introduced": 1
        }
      ],
      "blightmists": [
        {
          "category": "Blightfumes",
          "subcategory": "Blightmists",
          "name": "Nullmist",
          "rarity": 27,
          "description": [
            "Lorem, ipsum dolor sit amet consectetur adipisicing elit. Animi iure omnis perspiciatis veritatis molestiae sit accusamus tenetur, porro quibusdam eum!"
          ],
          "introduced": 1
        },
        {
          "category": "Blightfumes",
          "subcategory": "Blightmists",
          "name": "Magnimist",
          "rarity": 9,
          "description": [
            "Lorem, ipsum dolor sit amet consectetur adipisicing elit. Animi iure omnis perspiciatis veritatis molestiae sit accusamus tenetur, porro quibusdam eum!"
          ],
          "introduced": 1
        },
        {
          "category": "Blightfumes",
          "subcategory": "Blightmists",
          "name": "Intermist",
          "rarity": 1,
          "description": [
            "Lorem, ipsum dolor sit amet consectetur adipisicing elit. Animi iure omnis perspiciatis veritatis molestiae sit accusamus tenetur, porro quibusdam eum!"
          ],
          "introduced": 1
        }
      ]
    },
    "blightflora": {
      "blightblooms": [
        {
          "category": "Blightflora",
          "subcategory": "Blightblooms",
          "name": "Shrineflower",
          "rarity": 27,
          "description": [
            "Lorem, ipsum dolor sit amet consectetur adipisicing elit. Animi iure omnis perspiciatis veritatis molestiae sit accusamus tenetur, porro quibusdam eum!"
          ],
          "introduced": 1
        },
        {
          "category": "Blightflora",
          "subcategory": "Blightblooms",
          "name": "Hydrobloom",
          "rarity": 9,
          "description": [
            "Lorem, ipsum dolor sit amet consectetur adipisicing elit. Animi iure omnis perspiciatis veritatis molestiae sit accusamus tenetur, porro quibusdam eum!"
          ],
          "introduced": 1
        },
        {
          "category": "Blightflora",
          "subcategory": "Blightblooms",
          "name": "Shimmering Nightblight",
          "rarity": 1,
          "description": [
            "Lorem, ipsum dolor sit amet consectetur adipisicing elit. Animi iure omnis perspiciatis veritatis molestiae sit accusamus tenetur, porro quibusdam eum!"
          ],
          "introduced": 1
        }
      ],
      "blightpillars": [
        {
          "category": "Blightflora",
          "subcategory": "Blightpillars",
          "name": "Whitespire",
          "rarity": 27,
          "description": [
            "Lorem, ipsum dolor sit amet consectetur adipisicing elit. Animi iure omnis perspiciatis veritatis molestiae sit accusamus tenetur, porro quibusdam eum!"
          ],
          "introduced": 1
        },
        {
          "category": "Blightflora",
          "subcategory": "Blightpillars",
          "name": "Greyspire",
          "rarity": 9,
          "description": [
            "Lorem, ipsum dolor sit amet consectetur adipisicing elit. Animi iure omnis perspiciatis veritatis molestiae sit accusamus tenetur, porro quibusdam eum!"
          ],
          "introduced": 1
        },
        {
          "category": "Blightflora",
          "subcategory": "Blightpillars",
          "name": "Blackspire",
          "rarity": 1,
          "description": [
            "Lorem, ipsum dolor sit amet consectetur adipisicing elit. Animi iure omnis perspiciatis veritatis molestiae sit accusamus tenetur, porro quibusdam eum!"
          ],
          "introduced": 1
        }
      ],
      "blightsnarls": [
        {
          "category": "Blightflora",
          "subcategory": "Blightsnarls",
          "name": "Silverclutch",
          "rarity": 27,
          "description": [
            "Lorem, ipsum dolor sit amet consectetur adipisicing elit. Animi iure omnis perspiciatis veritatis molestiae sit accusamus tenetur, porro quibusdam eum!"
          ],
          "introduced": 1
        },
        {
          "category": "Blightflora",
          "subcategory": "Blightsnarls",
          "name": "Wenderweave",
          "rarity": 9,
          "description": [
            "Lorem, ipsum dolor sit amet consectetur adipisicing elit. Animi iure omnis perspiciatis veritatis molestiae sit accusamus tenetur, porro quibusdam eum!"
          ],
          "introduced": 1
        },
        {
          "category": "Blightflora",
          "subcategory": "Blightsnarls",
          "name": "Darkcoil",
          "rarity": 1,
          "description": [
            "Lorem, ipsum dolor sit amet consectetur adipisicing elit. Animi iure omnis perspiciatis veritatis molestiae sit accusamus tenetur, porro quibusdam eum!"
          ],
          "introduced": 1
        }
      ]
    },
    "blightfungi": {
      "blightshrooms": [
        {
          "category": "Blightfungi",
          "subcategory": "Blightshrooms",
          "name": "Darkcoil",
          "rarity": 27,
          "description": [
            "Lorem, ipsum dolor sit amet consectetur adipisicing elit. Animi iure omnis perspiciatis veritatis molestiae sit accusamus tenetur, porro quibusdam eum!"
          ],
          "introduced": 1
        },
        {
          "category": "Blightfungi",
          "subcategory": "Blightshrooms",
          "name": "Metashroom",
          "rarity": 9,
          "description": [
            "Lorem, ipsum dolor sit amet consectetur adipisicing elit. Animi iure omnis perspiciatis veritatis molestiae sit accusamus tenetur, porro quibusdam eum!"
          ],
          "introduced": 1
        },
        {
          "category": "Blightfungi",
          "subcategory": "Blightshrooms",
          "name": "Tranceloom",
          "rarity": 1,
          "description": [
            "Lorem, ipsum dolor sit amet consectetur adipisicing elit. Animi iure omnis perspiciatis veritatis molestiae sit accusamus tenetur, porro quibusdam eum!"
          ],
          "introduced": 1
        }
      ],
      "blightbleeds": [
        {
          "category": "Blightfungi",
          "subcategory": "Blightbleeds",
          "name": "Trickelpus",
          "rarity": 27,
          "description": [
            "Lorem, ipsum dolor sit amet consectetur adipisicing elit. Animi iure omnis perspiciatis veritatis molestiae sit accusamus tenetur, porro quibusdam eum!"
          ],
          "introduced": 1
        },
        {
          "category": "Blightfungi",
          "subcategory": "Blightbleeds",
          "name": "Rockmole",
          "rarity": 9,
          "description": [
            "Lorem, ipsum dolor sit amet consectetur adipisicing elit. Animi iure omnis perspiciatis veritatis molestiae sit accusamus tenetur, porro quibusdam eum!"
          ],
          "introduced": 1
        },
        {
          "category": "Blightfungi",
          "subcategory": "Blightbleeds",
          "name": "Achromatic Ooze",
          "rarity": 1,
          "description": [
            "Lorem, ipsum dolor sit amet consectetur adipisicing elit. Animi iure omnis perspiciatis veritatis molestiae sit accusamus tenetur, porro quibusdam eum!"
          ],
          "introduced": 1
        }
      ],
      "sporesprawls": [
        {
          "category": "Blightfungi",
          "subcategory": "Sporesprawls",
          "name": "Sporesprawl1",
          "rarity": 27,
          "description": [
            "Lorem, ipsum dolor sit amet consectetur adipisicing elit. Animi iure omnis perspiciatis veritatis molestiae sit accusamus tenetur, porro quibusdam eum!"
          ],
          "introduced": 1
        },
        {
          "category": "Blightfungi",
          "subcategory": "Sporesprawls",
          "name": "Sporesprawl2",
          "rarity": 9,
          "description": [
            "Lorem, ipsum dolor sit amet consectetur adipisicing elit. Animi iure omnis perspiciatis veritatis molestiae sit accusamus tenetur, porro quibusdam eum!"
          ],
          "introduced": 1
        },
        {
          "category": "Blightfungi",
          "subcategory": "Sporesprawls",
          "name": "Sporesprawl3",
          "rarity": 1,
          "description": [
            "Lorem, ipsum dolor sit amet consectetur adipisicing elit. Animi iure omnis perspiciatis veritatis molestiae sit accusamus tenetur, porro quibusdam eum!"
          ],
          "introduced": 1
        }
      ]
    },
    "blightanomalies": {
      "tokens": [
        {
          "category": "Blightanomalies",
          "subcategory": "Blightanomalies",
          "name": "Dusk Orb",
          "rarity": 27,
          "description": [
            "Lorem, ipsum dolor sit amet consectetur adipisicing elit. Animi iure omnis perspiciatis veritatis molestiae sit accusamus tenetur, porro quibusdam eum!"
          ],
          "introduced": 1
        },
        {
          "category": "Blightanomalies",
          "subcategory": "Blightanomalies",
          "name": "Token2",
          "rarity": 9,
          "description": [
            "Lorem, ipsum dolor sit amet consectetur adipisicing elit. Animi iure omnis perspiciatis veritatis molestiae sit accusamus tenetur, porro quibusdam eum!"
          ],
          "introduced": 1
        },
        {
          "category": "Blightanomalies",
          "subcategory": "Blightanomalies",
          "name": "Token3",
          "rarity": 1,
          "description": [
            "Lorem, ipsum dolor sit amet consectetur adipisicing elit. Animi iure omnis perspiciatis veritatis molestiae sit accusamus tenetur, porro quibusdam eum!"
          ],
          "introduced": 1
        }
      ],
      "loci": [
        {
          "category": "Blightanomalies",
          "subcategory": "Blightanomalies",
          "name": "Locus1",
          "rarity": 27,
          "description": [
            "Lorem, ipsum dolor sit amet consectetur adipisicing elit. Animi iure omnis perspiciatis veritatis molestiae sit accusamus tenetur, porro quibusdam eum!"
          ],
          "introduced": 1
        },
        {
          "category": "Blightanomalies",
          "subcategory": "Blightanomalies",
          "name": "Locus2",
          "rarity": 9,
          "description": [
            "Lorem, ipsum dolor sit amet consectetur adipisicing elit. Animi iure omnis perspiciatis veritatis molestiae sit accusamus tenetur, porro quibusdam eum!"
          ],
          "introduced": 1
        },
        {
          "category": "Blightanomalies",
          "subcategory": "Blightanomalies",
          "name": "Locus3",
          "rarity": 1,
          "description": [
            "Lorem, ipsum dolor sit amet consectetur adipisicing elit. Animi iure omnis perspiciatis veritatis molestiae sit accusamus tenetur, porro quibusdam eum!"
          ],
          "introduced": 1
        }
      ],
      "vestiges": [
        {
          "category": "Blightanomalies",
          "subcategory": "Blightanomalies",
          "name": "Lightmare Prism",
          "rarity": 27,
          "description": [
            "Lorem, ipsum dolor sit amet consectetur adipisicing elit. Animi iure omnis perspiciatis veritatis molestiae sit accusamus tenetur, porro quibusdam eum!"
          ],
          "introduced": 1
        },
        {
          "category": "Blightanomalies",
          "subcategory": "Blightanomalies",
          "name": "Vestige2",
          "rarity": 9,
          "description": [
            "Lorem, ipsum dolor sit amet consectetur adipisicing elit. Animi iure omnis perspiciatis veritatis molestiae sit accusamus tenetur, porro quibusdam eum!"
          ],
          "introduced": 1
        },
        {
          "category": "Blightanomalies",
          "subcategory": "Blightanomalies",
          "name": "Vestige3",
          "rarity": 1,
          "description": [
            "Lorem, ipsum dolor sit amet consectetur adipisicing elit. Animi iure omnis perspiciatis veritatis molestiae sit accusamus tenetur, porro quibusdam eum!"
          ],
          "introduced": 1
        }
      ]
    }
  },
  "description": [
    "Over time, blightsources have been organized into groupings based on apparent features. This system of organization differs from region to region, but the Shrouded Theocracy uses a list of six major categories, each with subcategories clustered within. These are: 'Blightstones', 'Blightichors', 'Blightfumes', 'Blightflora', 'Blightfungi', and 'Blightanomalies'.",
    "Some blightsources are more or less useful than others. Some can be used as fuel, as magical catalysts, molded into armor, or store magical energies, among other applications. The Blightbane Guild serves as the most prominent buyer, consumer, and distributer of most varieties of blightsources. This is their major source of income, and the backbone upon which they pay their staff, contractors, and bankroll research endeavors.",
    "Some Blight Seekers specialize in harvesting and transporting blightsources. They are known as 'Harvesters', but among them are the porters and guards. This work is more lucrative than taking on blightbeast culling contracts, but it comes with a unique set of risks. They must collect resources in a battlefield where they must trust that their guards can protect them, focusing on extracting what they need without damaging the product. For this reason, the Guild requires that all Harvesters be full seekers, trained to defend themselves if need be. However, if a Harvester needs to defend themselves, it is often too late."
  ],
  "information": [
    {
      "category": "Blightstones",
      "description": [
        "Blightstones are materials ranging from the metals smelted from blightfoils, to the crystal clusters of semi-transparent crystali, to the dense leylode deposits. They are more easily found in desert, tundras, and marine biome festerfonts. Conversely, they are less likely to be found in grassland biome festerfonts.",
        "Blightstones are primarily harvested using miner's picks, or jeweler's chisels for the more delicate Crystali. Some guilds, however, have the resources to equip their harvesters with magitech harvesting tools, or equipment of wholly mechanical make. These guilds are few and far between, and they are discouraged by regular losses to blightbeasts, or high maintenance costs of expensive and fickle equipment."
      ],
      "subcategories": [
        {
          "category": "Blightstones",
          "subcategory": "Blightfoils",
          "description": [
            "Blightfoils are metals smelted from minerals carrying inherently magical qualities. One would think that this would make such materials exceptionally valuable, but it is not so. Their worth is inflated due to the metals being difficult to work with and even more difficult to find a use for. Predicting how a blightfoil will interact with any given spell is tricky. Mages are notoriously reckless, but who uses a blightfoil catalyst is going a step further than the norm in regards to disregard for personal safety.",
            "The most popular blightfoil would have to be forslone, which effectively cloaks the bearer in a magically repellant shield. It is more complicated than that, but defense against magic is one thing anyone will upend their coin purses for. Other metals are sometimes used for decoration, such as the beautiful voidshimmer, with its midnight black base, full of everlasting purple sparkles."
          ]
        },
        {
          "category": "Blightstones",
          "subcategory": "Crystali",
          "description": [
            "Crystali are found in fragile clusters, often glittering in the caves of festerfonts, far off the beaten path. They are unique for their ability to store and expel magical energy. For this reason, they are used as vessels for energy, and portable spell containers. Some crystali are durable enough to expend the stored spell multiple times, but these are rare, and most simple shatter once they are used.",
            "As disposable as these materials are, a merchant is always willing to buy one, no matter how small the crystal fragment may be. Harvesting them is no easy task. They are prone to shattering at the lightest touch. That goes doubly for using them to store a spell. Commonly, vitality and clarity shards are formed from small crystals of apertrite, which is the least expensive crystali on the market."
          ]
        },
        {
          "category": "Blightstones",
          "subcategory": "Lylodes",
          "description": [
            "Leylodes are dense deposits found in the depths of festerfont rock, or less commonly, on the surface said blighted land. Though festerfonts spawn blightbeasts and blightsources seemingly randomly and spontaneously, leylodes have been observed to proliferate from existing deposits. In this way, a harvest crew can leave a small portion of easily-accessible leylode untouched, until it grows enough to tap into once more. That is, if another crew hasn't gotten their first.",
            "Harvesting leylodes is easy enough, as the real chore is transporting any sizable quantity out of the festerfont and getting a good price for it. Fortunately, the price of charke, the most commonly encountered leylode, is always high enough to make it worth the effort. The Guild will always buy other leylodes, especially curos, for which they remain the sole buyer."
          ]
        }
      ]
    },
    {
      "category": "Blightichors",
      "description": [
        "Lorem, ipsum dolor sit amet consectetur adipisicing elit. Animi iure omnis perspiciatis veritatis molestiae sit accusamus tenetur, porro quibusdam eum!"
      ],
      "subcategories": [
        {
          "category": "Blightichors",
          "subcategory": "Lifeblight",
          "description": [
            "Lorem, ipsum dolor sit amet consectetur adipisicing elit. Animi iure omnis perspiciatis veritatis molestiae sit accusamus tenetur, porro quibusdam eum!"
          ]
        },
        {
          "category": "Blightichors",
          "subcategory": "Blightvenoms",
          "description": [
            "Lorem, ipsum dolor sit amet consectetur adipisicing elit. Animi iure omnis perspiciatis veritatis molestiae sit accusamus tenetur, porro quibusdam eum!"
          ]
        },
        {
          "category": "Blightichors",
          "subcategory": "Blightmares",
          "description": [
            "Lorem, ipsum dolor sit amet consectetur adipisicing elit. Animi iure omnis perspiciatis veritatis molestiae sit accusamus tenetur, porro quibusdam eum!"
          ]
        }
      ]
    },
    {
      "category": "Blightfumes",
      "description": [
        "Lorem, ipsum dolor sit amet consectetur adipisicing elit. Animi iure omnis perspiciatis veritatis molestiae sit accusamus tenetur, porro quibusdam eum!"
      ],
      "subcategories": [
        {
          "category": "Blightfumes",
          "subcategory": "Rushblight",
          "description": [
            "Lorem, ipsum dolor sit amet consectetur adipisicing elit. Animi iure omnis perspiciatis veritatis molestiae sit accusamus tenetur, porro quibusdam eum!"
          ]
        },
        {
          "category": "Blightfumes",
          "subcategory": "Miasmeta",
          "description": [
            "Lorem, ipsum dolor sit amet consectetur adipisicing elit. Animi iure omnis perspiciatis veritatis molestiae sit accusamus tenetur, porro quibusdam eum!"
          ]
        },
        {
          "category": "Blightfumes",
          "subcategory": "Blightmists",
          "description": [
            "Lorem, ipsum dolor sit amet consectetur adipisicing elit. Animi iure omnis perspiciatis veritatis molestiae sit accusamus tenetur, porro quibusdam eum!"
          ]
        }
      ]
    },
    {
      "category": "Blightflora",
      "description": [
        "Lorem, ipsum dolor sit amet consectetur adipisicing elit. Animi iure omnis perspiciatis veritatis molestiae sit accusamus tenetur, porro quibusdam eum!"
      ],
      "subcategories": [
        {
          "category": "Blightflora",
          "subcategory": "Blightblooms",
          "description": [
            "Lorem, ipsum dolor sit amet consectetur adipisicing elit. Animi iure omnis perspiciatis veritatis molestiae sit accusamus tenetur, porro quibusdam eum!"
          ]
        },
        {
          "category": "Blightflora",
          "subcategory": "Blightpillars",
          "description": [
            "Lorem, ipsum dolor sit amet consectetur adipisicing elit. Animi iure omnis perspiciatis veritatis molestiae sit accusamus tenetur, porro quibusdam eum!"
          ]
        },
        {
          "category": "Blightflora",
          "subcategory": "Blightsnarls",
          "description": [
            "Lorem, ipsum dolor sit amet consectetur adipisicing elit. Animi iure omnis perspiciatis veritatis molestiae sit accusamus tenetur, porro quibusdam eum!"
          ]
        }
      ]
    },
    {
      "category": "Blightfungi",
      "description": [
        "Lorem, ipsum dolor sit amet consectetur adipisicing elit. Animi iure omnis perspiciatis veritatis molestiae sit accusamus tenetur, porro quibusdam eum!"
      ],
      "subcategories": [
        {
          "category": "Blightfungi",
          "subcategory": "Blightshrooms",
          "description": [
            "Lorem, ipsum dolor sit amet consectetur adipisicing elit. Animi iure omnis perspiciatis veritatis molestiae sit accusamus tenetur, porro quibusdam eum!"
          ]
        },
        {
          "category": "Blightfungi",
          "subcategory": "Blightbleeds",
          "description": [
            "Lorem, ipsum dolor sit amet consectetur adipisicing elit. Animi iure omnis perspiciatis veritatis molestiae sit accusamus tenetur, porro quibusdam eum!"
          ]
        },
        {
          "category": "Blightfungi",
          "subcategory": "Sporesprawls",
          "description": [
            "Lorem, ipsum dolor sit amet consectetur adipisicing elit. Animi iure omnis perspiciatis veritatis molestiae sit accusamus tenetur, porro quibusdam eum!"
          ]
        }
      ]
    },
    {
      "category": "Blightanomalies",
      "description": [
        "Lorem, ipsum dolor sit amet consectetur adipisicing elit. Animi iure omnis perspiciatis veritatis molestiae sit accusamus tenetur, porro quibusdam eum!"
      ],
      "subcategories": [
        {
          "category": "Blightanomalies",
          "subcategory": "Tokens",
          "description": [
            "Lorem, ipsum dolor sit amet consectetur adipisicing elit. Animi iure omnis perspiciatis veritatis molestiae sit accusamus tenetur, porro quibusdam eum!"
          ]
        },
        {
          "category": "Blightanomalies",
          "subcategory": "Loci",
          "description": [
            "Lorem, ipsum dolor sit amet consectetur adipisicing elit. Animi iure omnis perspiciatis veritatis molestiae sit accusamus tenetur, porro quibusdam eum!"
          ]
        },
        {
          "category": "Blightanomalies",
          "subcategory": "Vestiges",
          "description": [
            "Lorem, ipsum dolor sit amet consectetur adipisicing elit. Animi iure omnis perspiciatis veritatis molestiae sit accusamus tenetur, porro quibusdam eum!"
          ]
        }
      ]
    }
  ]
}
